AUTHORS
ChangeLog
LICENSE.md
README.rst
requirements.txt
setup.cfg
setup.py
docs/Makefile
docs/haproxyadmin.ipynb
docs/make.bat
docs/.ipynb_checkpoints/haproxyadmin-checkpoint.ipynb
docs/source/TODO.rst
docs/source/changelog.rst
docs/source/conf.py
docs/source/index.rst
docs/source/introduction.rst
docs/source/dev/api.rst
docs/source/user/backend.rst
docs/source/user/frontend.rst
docs/source/user/guide.rst
docs/source/user/haproxy.rst
docs/source/user/server.rst
haproxyadmin/__init__.py
haproxyadmin/backend.py
haproxyadmin/command_status.py
haproxyadmin/exceptions.py
haproxyadmin/frontend.py
haproxyadmin/haproxy.py
haproxyadmin/server.py
haproxyadmin/utils.py
haproxyadmin.egg-info/PKG-INFO
haproxyadmin.egg-info/SOURCES.txt
haproxyadmin.egg-info/dependency_links.txt
haproxyadmin.egg-info/not-zip-safe
haproxyadmin.egg-info/pbr.json
haproxyadmin.egg-info/requires.txt
haproxyadmin.egg-info/top_level.txt
haproxyadmin/internal/__init__.py
haproxyadmin/internal/backend.py
haproxyadmin/internal/frontend.py
haproxyadmin/internal/haproxy.py
haproxyadmin/internal/server.py
tools/generate_constants_for_metrics.py
tools/get_errors_messages.sh
tools/haproxy.cfg