Metadata-Version: 1.2
Name: haproxyadmin
Version: 0.2.4
Summary: A library to work with HAProxy via the stats socket
Home-page: UNKNOWN
Author: Pavlos Parissis
Author-email: pavlos.parissis@gmail.com
Maintainer: Pavlos Parissis
Maintainer-email: pavlos.parissis@gmail.com
License: Apache 2.0
Keywords: haproxy
Platform: UNKNOWN
Classifier: Development Status :: 5 - Production/Stable
Classifier: Environment :: Console
Classifier: Intended Audience :: Information Technology
Classifier: Intended Audience :: System Administrators
Classifier: Natural Language :: English
Classifier: Operating System :: POSIX
Classifier: Programming Language :: Python :: 2.7
Classifier: Programming Language :: Python :: 3.4
Classifier: Topic :: Utilities
